{
  "kind": "singleType",
  "collectionName": "homes",
  "info": {
    "singularName": "home",
    "pluralName": "homes",
    "displayName": "Home",
    "description": ""
  },
  "options": {
    "draftAndPublish": true
  },
  "pluginOptions": {
    "i18n": {
      "localized": true
    }
  },
  "attributes": {
    "hero_banners": {
      "displayName": "Hero Banners",
      "type": "component",
      "repeatable": true,
      "component": "home.hero-banners",
      "pluginOptions": {
        "i18n": {
          "localized": true
        }
      }
    },
    "middle_banners": {
      "type": "component",
      "repeatable": true,
      "component": "home.hero-banners",
      "pluginOptions": {
        "i18n": {
          "localized": true
        }
      }
    },
    "bottom_bunners": {
      "type": "component",
      "repeatable": true,
      "component": "home.hero-banners",
      "pluginOptions": {
        "i18n": {
          "localized": true
        }
      }
    },
    "faq_links": {
      "type": "component",
      "repeatable": true,
      "component": "home.hero-banners",
      "pluginOptions": {
        "i18n": {
          "localized": true
        }
      }
    },
    "subscribe": {
      "type": "boolean",
      "pluginOptions": {
        "i18n": {
          "localized": true
        }
      }
    },
    "brandsLogo": {
      "type": "media",
      "multiple": true,
      "required": false,
      "allowedTypes": [
        "images",
        "files",
        "videos",
        "audios"
      ],
      "pluginOptions": {
        "i18n": {
          "localized": true
        }
      }
    },
    "terms": {
      "displayName": "terms",
      "type": "component",
      "repeatable": true,
      "component": "home.terms",
      "pluginOptions": {
        "i18n": {
          "localized": true
        }
      }
    }
  }
}
